Workbook
Name Image1: Code!$A$31
Name Image2: Code!$A$32

Sheet Final Quotation
D1: Quotation
A2: To,
A3: =VLOOKUP('Customer Costing'!D4,'Customer Database'!A:B,2,0)&" "&'Customer Costing'!D4 -> Salutation Choose Contact Person | D3: Date: | E3: ='Customer Costing'!B2 -> 46097
A4: =IFERROR(VLOOKUP('Customer Costing'!D4,'Customer Database'!A:F,6,0), "Not Found") -> Business Account Name | D4: Quote #: | E4: ='Customer Costing'!D3 -> 0 | G4: Terms and Conditions
A5: =IFERROR(VLOOKUP('Customer Costing'!D4,'Customer Database'!A:E,3,0), "Not Found") -> Phone | D5: Quote Valid Until | E5: =E3+30 -> 46127 | G5: • | H5: Offer for complete delivery: Prices valid for full order alone.
A6: =IFERROR(VLOOKUP('Customer Costing'!D4,'Customer Database'!A:E,5,0), "Not Found") -> Address | D6: Customer ID: | E6: =VLOOKUP('Customer Costing'!B4,Code!G:K,5,0) -> #N/A | G6: • | H6: Payment Terms | I6: ='Customer Costing'!D5 -> Select payment terms
D7: Issued by | E7: ='Customer Costing'!B3 -> Quote Prepared By | G7: • | H7: Warranty | I7: =IF('Customer Costing'!F4="General",Code!D15,IF('Customer Costing'!F4="spareparts",Code!D16,IF('Customer Costing'!F4="items+spareparts",Code!D15&". "&Code!D16,"Please Select Est. Delivery in costing"))) -> Please Select Est. Delivery in costing
G8: • | H8: Order Cancellation: | I8: Charges applicable according to OEM terms
G9: • | H9: Delivery time: | I9: ="Approx. "&" "&'Customer Costing'!F2&"; exact period confirmed after order placement." -> Approx. To be Known after order is placed; exact period confirmed after order placement.
A10: ="Your Reference"&": "&'Customer Costing'!D1 -> Your Reference: [Input Manually] | G10: • | H10: Delivery Terms: | I10: ='Customer Costing'!F3 -> DAP Bahrain at your store or PH Trading
A11: Dear Sir, We appreciate your interest in our products and thank you for your inquiry. Enclosed, you will find our quotation tailored for your specific application. Our proposal is prepared based on the details and specifications provided by you. | G11: • | H11: Installation | I11: =IF('Customer Costing'!H3="No","Excluded / not in our scope","Check Quotation for pricing") -> Excluded / not in our scope
G12: • | H12: Commissioning | I12: =IF('Customer Costing'!H4="No","Excluded / not in our scope","Check Quotation for pricing") -> Excluded / not in our scope
G13: • | H13: Testing | I13: =IF('Customer Costing'!H5="No","Excluded / not in our scope","Check Quotation for pricing") -> Excluded / not in our scope
G14: • | H14: Test Certificate | I14: =VLOOKUP('Customer Costing'!H1,Code!A40:B42,2,0) -> Additional charges applicable as per OEM terms
G15: • | H15: Certificate of Origin | I15: =VLOOKUP('Customer Costing'!H1,Code!A40:B42,2,0) -> Additional charges applicable as per OEM terms
A16: Sr. No. | B16: Item Description, Order Code* | C16: Unit cost | D16: Qty | E16: Amount (BHD) | G16: • | H16: Country of origin | I16: =VLOOKUP('Customer Costing'!F5,Code!C23:D30,2,0) -> Select Country
A17: 1 | B17: ='Customer Costing'!C8&CHAR(10)&'Customer Costing'!C9&CHAR(10)&'Customer Costing'!C10 -> Electronics Micropilot FMR6x Model no.: XPF0038-1014/0 (XPF0038-1) | C17: ='Customer Costing'!$C$30 -> 692 | D17: ='Customer Costing'!C$11 -> 1 | E17: =C17*D17 -> 692 | G17: • | H17: Certificate of Conformity | I17: =VLOOKUP('Customer Costing'!H1,Code!A40:B42,2,0) -> Additional charges applicable as per OEM terms
A18: 2 | B18: ='Customer Costing'!D8&CHAR(10)&'Customer Costing'!D9&CHAR(10)&'Customer Costing'!D10 -> I/O mod.Level,2-wr.4-20mA,HART,Ex,LP,V3 Model no.: 71364026 [Specifiation 2] | C18: ='Customer Costing'!$D$30 -> 227 | D18: ='Customer Costing'!D$11 -> 1 | E18: =C18*D18 -> 227 | G18: • | H18: Please check Annexure 1 for detailed Order Code(s)
A19: 3 | B19: ='Customer Costing'!E8&CHAR(10)&'Customer Costing'!E9&CHAR(10)&'Customer Costing'!E10 -> Remote Display FHX50B Model no.: FHX50B-1P79/0 (FHX50B-BGEB3+Z1) | C19: ='Customer Costing'!$E$30 -> 333 | D19: ='Customer Costing'!E$11 -> 1 | E19: =C19*D19 -> 333 | G19: • | H19: This proposal is subject to general terms and conditions of delivery and sales as per OEM.
A20: 4 | B20: ='Customer Costing'!F8&CHAR(10)&'Customer Costing'!F9&CHAR(10)&'Customer Costing'!F10 -> [Product 4] [Specifiation 4] | C20: ='Customer Costing'!$F$30 -> 0 | D20: ='Customer Costing'!F$11 -> 0 | E20: =C20*D20 -> 0 | G20: • | H20: We have chosen our instruments according to the specifications given. However, we kindly ask you to thoroughly check the technical data with respect to suitability for your application.
A21: 5 | B21: ='Customer Costing'!G8&CHAR(10)&'Customer Costing'!G9&CHAR(10)&'Customer Costing'!G10 -> [Product 5] [Specifiation 5] | C21: ='Customer Costing'!$G$30 -> 0 | D21: ='Customer Costing'!G$11 -> 0 | E21: =C21*D21 -> 0
A22: 6 | B22: ='Customer Costing'!H8&CHAR(10)&'Customer Costing'!H9&CHAR(10)&'Customer Costing'!H10 -> [Product 6] [Specifiation 6] | C22: ='Customer Costing'!$H$30 -> 0 | D22: ='Customer Costing'!H$11 -> 0 | E22: =C22*D22 -> 0 | H22: This quotation is confidential.
A23: 7 | B23: ='Customer Costing'!I8&CHAR(10)&'Customer Costing'!I9&CHAR(10)&'Customer Costing'!I10 -> [Product 7] [Model 7] [Specifiation 7] | C23: ='Customer Costing'!$I$30 -> 0 | D23: ='Customer Costing'!I$11 -> 0 | E23: =C23*D23 -> 0
A24: 8 | B24: ='Customer Costing'!J8&CHAR(10)&'Customer Costing'!J9&CHAR(10)&'Customer Costing'!J10 -> [Product 8] [Model 8] [Specifiation 8] | C24: ='Customer Costing'!$J$30 -> 0 | D24: ='Customer Costing'!J$11 -> 0 | E24: =C24*D24 -> 0 | H24: Best Regards,
A25: 9 | B25: ='Customer Costing'!K8&CHAR(10)&'Customer Costing'!K9&CHAR(10)&'Customer Costing'!K10 -> [Product 9] [Model 9] [Specifiation 9] | C25: ='Customer Costing'!$K$30 -> 0 | D25: ='Customer Costing'!K$11 -> 0 | E25: =C25*D25 -> 0 | H25: =E7 -> Quote Prepared By
A26: 10 | B26: ='Customer Costing'!L8&CHAR(10)&'Customer Costing'!L9&CHAR(10)&'Customer Costing'!L10 -> [Product 10] [Model 10] [Specifiation 10] | C26: ='Customer Costing'!$L$30 -> 0 | D26: ='Customer Costing'!L$11 -> 0 | E26: =C26*D26 -> 0 | H26: =VLOOKUP(H25,Code!A1:B7,2,0) -> Designation
A27: 11 | B27: ='Customer Costing'!M9&CHAR(10)&'Customer Costing'!M10&CHAR(10)&'Customer Costing'!M11 -> [Model 11] [Specifiation 11] | C27: ='Customer Costing'!$M$30 -> 0 | D27: ='Customer Costing'!M$11 -> 0 | E27: =C27*D27 -> 0 | H27: ="Mob: "&VLOOKUP(H25,Code!A1:D8,3,0) -> Mob: Contact Number
A28: 12 | B28: ='Customer Costing'!N10&CHAR(10)&'Customer Costing'!N11&CHAR(10)&'Customer Costing'!N12 -> [Specifiation 12] | C28: ='Customer Costing'!$N$30 -> 0 | D28: ='Customer Costing'!N$11 -> 0 | E28: =C28*D28 -> 0 | H28: ="Email: "&VLOOKUP(H25,Code!A1:D8,4,0) -> Email: Email
B29: ='Customer Costing'!Q8&CHAR(10)&'Customer Costing'!Q9&CHAR(10)&'Customer Costing'!Q10 | H29: ='Customer Costing'!B1 -> PH Trading WLL
B30: ='Customer Costing'!R8&CHAR(10)&'Customer Costing'!R9&CHAR(10)&'Customer Costing'!R10 | H30: www.platinumholdings.com.bh
D33: SUBTOTAL | E33: =SUM(E17:E28) -> 1252
D34: DISCOUNT | E34: 0
D35: VAT 10% | E35: =(E33+E34)*0.1 -> 125.2
D36: TOTAL (BHD) | E36: =E33-E34+E35 -> 1377.2
H40: Thank you for your business! Should you have any enquiries concerning this quote, Email support@platinumholdings.com.bh
A44: Paste on page 1 | G44: Paste on page 2

Sheet Customer Costing
A1: Division | B1: PH Trading WLL | C1: RFQ Refference | D1: [Input Manually] | G1: COC and COO | H1: No
A2: Date | B2: =TODAY() -> 46097 | C2: Folder Number | E2: Est. Delivery | F2: To be Known after order is placed | G2: Test Certificate | H2: Select Certificates
A3: Prepared By | B3: Quote Prepared By | C3: Costing ID | E3: Delivery Terms | F3: DAP Bahrain at your store or PH Trading | G3: Installation | H3: No
A4: Customer | C4: Contact Person | D4: Choose Contact Person | E4: order Type | F4: Select order type | G4: Commisioning | H4: No
A5: Reference | B5: Email | C5: Payment Terms | D5: Select payment terms | E5: Country of Origin | F5: Country of Origin | G5: Testing | H5: No
A7: Supplier | C7: EH | D7: EH | E7: Principle Name | F7: Principle Name | G7: Principle Name | H7: Principle Name | I7: Principle Name | J7: Principle Name | K7: Principle Name | L7: Principle Name | M7: Principle Name | N7: Principle Name | O7: Total for Order
A8: Equipment | C8: Electronics Micropilot FMR6x | D8: I/O mod.Level,2-wr.4-20mA,HART,Ex,LP,V3 | E8: Remote Display FHX50B | F8: [Product 4] | G8: [Product 5] | H8: [Product 6] | I8: [Product 7] | J8: [Product 8] | K8: [Product 9] | L8: [Product 10] | M8: [Product 11] | N8: [Product 12]
A9: Model | C9: Model no.: XPF0038-1014/0 | D9: Model no.: 71364026 | E9: Model no.: FHX50B-1P79/0 | I9: [Model 7] | J9: [Model 8] | K9: [Model 9] | L9: [Model 10] | M9: [Model 11] | N9: [Model 12]
A10: Specification / Order Code | C10: (XPF0038-1) | D10: [Specifiation 2] | E10: (FHX50B-BGEB3+Z1) | F10: [Specifiation 4] | G10: [Specifiation 5] | H10: [Specifiation 6] | I10: [Specifiation 7] | J10: [Specifiation 8] | K10: [Specifiation 9] | L10: [Specifiation 10] | M10: [Specifiation 11] | N10: [Specifiation 12]
A11: Currency | B11: Quantity | C11: 1 | D11: 1 | E11: 1
A12: EUR | B12: FOB | C12: 980.67 | D12: 321.08 | E12: 472.42 | O12: =SUM(C12:N12) -> 1774.17
B13: Total Price | C13: =(C12*C11) -> 980.67 | D13: =(D12*D11) -> 321.08 | E13: =(E12*E11) -> 472.42 | F13: =(F12*F11) -> 0 | G13: =(G12*G11) -> 0 | H13: =(H12*H11) -> 0 | I13: =(I12*I11) -> 0 | J13: =(J12*J11) -> 0 | ... N13: =(N12*N11) -> 0 | O13: =SUM(C13:N13) -> 1774.17
A14: EUR | B14: Freight | C14: =C12*0.17 -> 166.7139 | D14: =D12*0.17 -> 54.5836 | E14: =E12*0.17 -> 80.3114 | F14: =F12*0.09 -> 0 | G14: =G12*0.09 -> 0 | H14: =H12*0.09 -> 0 | I14: =I12*0.09 -> 0 | J14: =J12*0.09 -> 0 | K14: =K12*0.09 -> 0 | L14: =L12*0.09 -> 0 | M14: =M12*0.09 -> 0 | N14: =N12*0.09 -> 0 | O14: =SUM(C14:N14) -> 301.6089
B15: Total Frieght | C15: =(C12*C11)*0.09 -> 88.2603 | D15: =(D12*D11)*0.09 -> 28.8972 | E15: =(E12*E11)*0.09 -> 42.5178 | F15: =(F12*F11)*0.09 -> 0 | G15: =(G12*G11)*0.09 -> 0 | H15: =(H12*H11)*0.09 -> 0 | I15: =(I12*I11)*0.09 -> 0 | J15: =(J12*J11)*0.09 -> 0 | ... N15: =(N12*N11)*0.09 -> 0 | O15: =SUM(C15:N15) -> 159.6753
B16: Supplier's total price | C16: =C13+C15 -> 1068.9303 | D16: =(D12+D14)*D11 -> 375.6636 | E16: =(E12+E14)*E11 -> 552.7314 | F16: =(F12+F14)*F11 -> 0 | G16: =(G12+G14)*G11 -> 0 | H16: =(H12+H14)*H11 -> 0 | I16: =(I12+I14)*I11 -> 0 | J16: =(J12+J14)*J11 -> 0 | K16: =(K12+K14)*K11 -> 0 | ... N16: =(N12+N14)*N11 -> 0 | O16: =SUM(C16:N16) -> 1997.3253
B17: Exchange Rate to BHD | C17: =IF($A$12="EUR",0.45,0.39) -> 0.45 | D17: =IF($A$12="EUR",0.45,0.39) -> 0.45 | E17: =IF($A$12="EUR",0.45,0.39) -> 0.45 | F17: =IF($A$12="EUR",0.45,0.39) -> 0.45 | G17: =IF($A$12="EUR",0.45,0.39) -> 0.45 | H17: =IF($A$12="EUR",0.45,0.39) -> 0.45 | I17: =IF($A$12="EUR",0.45,0.39) -> 0.45 | J17: =IF($A$12="EUR",0.45,0.39) -> 0.45 | ... N17: =IF($A$12="EUR",0.45,0.39) -> 0.45
A18: BHD | B18: FOB | C18: =C12*C17 -> 441.3015 | D18: =D12*D17 -> 144.486 | E18: =E12*E17 -> 212.589 | F18: =F12*F17 -> 0 | G18: =G12*G17 -> 0 | H18: =H12*H17 -> 0 | I18: =I12*I17 -> 0 | J18: =J12*J17 -> 0 | ... N18: =N12*N17 -> 0 | O18: =SUM(C18:N18) -> 798.3765
A19: BHD | B19: Freight | C19: =C14*C17 -> 75.021255 | D19: =D14*D17 -> 24.56262 | E19: =E14*E17 -> 36.14013 | F19: =F14*F17 -> 0 | G19: =G14*G17 -> 0 | H19: =H14*H17 -> 0 | I19: =I14*I17 -> 0 | J19: =J14*J17 -> 0 | ... N19: =N14*N17 -> 0 | O19: =SUM(C19:N19) -> 135.72401
B20: C&F | C20: =C18+C19 -> 516.32275 | D20: =D18+D19 -> 169.04862 | E20: =E18+E19 -> 248.72913 | F20: =F18+F19 -> 0 | G20: =G18+G19 -> 0 | H20: =H18+H19 -> 0 | I20: =I18+I19 -> 0 | J20: =J18+J19 -> 0 | ... N20: =N18+N19 -> 0 | O20: =SUM(C20:N20) -> 934.1005
B21: Insurance | C21: 0 | D21: 0 | E21: 0 | F21: 0 | G21: 0 | H21: 0 | I21: 0 | J21: 0 | K21: 0 | L21: 0 | M21: 0 | N21: 0 | O21: =SUM(C21:N21) -> 0
A22: 0.05 | B22: Customs @ 6% | C22: =C20*$A$22 -> 25.816138 | D22: =D20*$A$22 -> 8.452431 | E22: =E20*$A$22 -> 12.436457 | F22: =F20*$A$22 -> 0 | G22: =G20*$A$22 -> 0 | H22: =H20*$A$22 -> 0 | I22: =I20*$A$22 -> 0 | J22: =J20*$A$22 -> 0 | ... N22: =N20*$A$22 -> 0 | O22: =SUM(C22:N22) -> 46.705025
B23: Landed Cost | C23: =SUM(C20:C22) -> 542.13889 | D23: =SUM(D20:D22) -> 177.50105 | E23: =SUM(E20:E22) -> 261.16559 | F23: =SUM(F20:F22) -> 0 | G23: =SUM(G20:G22) -> 0 | H23: =SUM(H20:H22) -> 0 | I23: =SUM(I20:I22) -> 0 | J23: =SUM(J20:J22) -> 0 | ... N23: =SUM(N20:N22) -> 0 | O23: =SUM(C23:N23) -> 980.80553
A24: 0.01 | B24: Handling @ 4% | C24: =C23*$A$24 -> 5.4213889 | D24: =D23*$A$24 -> 1.7750105 | E24: =E23*$A$24 -> 2.6116559 | F24: =F23*$A$24 -> 0 | G24: =G23*$A$24 -> 0 | H24: =H23*$A$24 -> 0 | I24: =I23*$A$24 -> 0 | J24: =J23*$A$24 -> 0 | ... N24: =N23*$A$24 -> 0 | O24: =SUM(C24:N24) -> 9.8080553
A25: 0.01 | B25: Finance Charges @1% | C25: =C23*$A$25 -> 5.4213889 | D25: =D23*$A$25 -> 1.7750105 | E25: =E23*$A$25 -> 2.6116559 | F25: =F23*$A$25 -> 0 | G25: =G23*$A$25 -> 0 | H25: =H23*$A$25 -> 0 | I25: =I23*$A$25 -> 0 | J25: =J23*$A$25 -> 0 | ... N25: =N23*$A$25 -> 0 | O25: =SUM(C25:N25) -> 9.8080553
B26: Other Costs | C26: 0 | D26: 0 | E26: 0 | F26: 0 | G26: 0 | H26: 0 | I26: 0 | J26: 0 | K26: 0 | L26: 0 | M26: 0 | N26: 0 | O26: =SUM(C26:N26) -> 0
B27: Total Cost | C27: =SUM(C23:C26) -> 552.98167 | D27: =SUM(D23:D26) -> 181.05107 | E27: =SUM(E23:E26) -> 266.3889 | F27: =SUM(F23:F26) -> 0 | G27: =SUM(G23:G26) -> 0 | H27: =SUM(H23:H26) -> 0 | I27: =SUM(I23:I26) -> 0 | J27: =SUM(J23:J26) -> 0 | ... N27: =SUM(N23:N26) -> 0 | O27: =SUM(C27*C11,D27*D11,E27*E11,F27*F11,G27*G11,H27*H11,I27*I11,J27*J11,K27*K11,L27*L11,M27*M11,N27*N11) -> 1000.4216
A28: 0.25 | B28: Markup @ 20% | C28: =C27*$A$28 -> 138.24542 | D28: =D27*$A$28 -> 45.262768 | E28: =E27*$A$28 -> 66.597225 | F28: =F27*$A$28 -> 0 | G28: =G27*$A$28 -> 0 | H28: =H27*$A$28 -> 0 | I28: =I27*$A$28 -> 0 | J28: =J27*$A$28 -> 0 | ... N28: =N27*$A$28 -> 0 | O28: =SUM(C28:N28) -> 250.10541
A29: Selling Price | C29: =C27+C28 -> 691.22709 | D29: =D27+D28 -> 226.31384 | E29: =E27+E28 -> 332.98612 | F29: =F27+F28 -> 0 | G29: =G27+G28 -> 0 | H29: =H27+H28 -> 0 | I29: =I27+I28 -> 0 | J29: =J27+J28 -> 0 | ... N29: =N27+N28 -> 0 | O29: =SUM(C29:N29) -> 1250.5271
A30: Suggested Price per unit | C30: =CEILING(C29,1) -> 692 | D30: =CEILING(D29,1) -> 227 | E30: =CEILING(E29,1) -> 333 | F30: =CEILING(F29,1) -> 0 | G30: =CEILING(G29,1) -> 0 | H30: =CEILING(H29,1) -> 0 | I30: =CEILING(I29,1) -> 0 | J30: =CEILING(J29,1) -> 0 | ... N30: =CEILING(N29,1) -> 0 | O30: =SUM(C30:N30) -> 1252
A31: Total Suggested Price | C31: =C30*C11 -> 692 | D31: =D30*D11 -> 227 | E31: =E30*E11 -> 333 | F31: =F30*F11 -> 0 | G31: =G30*G11 -> 0 | H31: =H30*H11 -> 0 | I31: =I30*I11 -> 0 | J31: =J30*J11 -> 0 | ... N31: =N30*N11 -> 0 | O31: =SUM(C31:N31) -> 1252
O32: =O31*10% -> 125.2 | P32: VAT (10%)
O33: =O31+O32 -> 1377.2 | P33: Grand Total
A34: Summary | C34: Total | D34: VAT | E34: Total with VAT
A35: Total PO value expected from Client | C35: =O31 -> 1252 | D35: =C35*0.1 -> 125.2 | E35: =C35+D35 -> 1377.2
A36: PH TRADING COST | C36: =O27 -> 1000.4216 | D36: =C36*0.1 -> 100.04216 | E36: =C36+D36 -> 1100.4638
A37: Profit | C37: =C35-C36 -> 251.57836 | D37: =D35-D36 -> 25.157836 | E37: =E35-E36 -> 276.7362
B38: Profit % | C38: =(C35-C36)/(C35) -> 0.20094118

Sheet Internal Quotation
D1: Quotation
A2: To,
A3: =VLOOKUP('Customer Costing'!D4,'Customer Database'!A:B,2,0)&" "&'Customer Costing'!D4 -> Salutation Choose Contact Person | D3: Date: | E3: ='Customer Costing'!B2 -> 46097
A4: =IFERROR(VLOOKUP('Customer Costing'!D4,'Customer Database'!A:F,6,0), "Not Found") -> Business Account Name | D4: Quote #: | E4: ='Customer Costing'!D3 -> 0 | G4: Terms and Conditions
A5: =IFERROR(VLOOKUP('Customer Costing'!D4,'Customer Database'!A:E,3,0), "Not Found") -> Phone | D5: Quote Valid Until | E5: =E3+30 -> 46127 | G5: • | H5: Offer for complete delivery: Prices valid for full order alone.
A6: =IFERROR(VLOOKUP('Customer Costing'!D4,'Customer Database'!A:E,5,0), "Not Found") -> Address | D6: Customer ID: | E6: =VLOOKUP('Customer Costing'!B4,Code!G:K,5,0) -> #N/A | G6: • | H6: Payment Terms | I6: ='Customer Costing'!D5 -> Select payment terms
D7: Issued by | E7: ='Customer Costing'!B3 -> Quote Prepared By | G7: • | H7: Warranty | I7: =IF('Customer Costing'!F4="General",Code!D15,IF('Customer Costing'!F4="spareparts",Code!D16,IF('Customer Costing'!F4="items+spareparts",Code!D15&". "&Code!D16,"Please Select Est. Delivery in costing"))) -> Please Select Est. Delivery in costing
G8: • | H8: Order Cancellation: | I8: Charges applicable according to OEM terms
G9: • | H9: Delivery time: | I9: ="Approx. "&" "&'Customer Costing'!F2&"; exact period confirmed after order placement." -> Approx. To be Known after order is placed; exact period confirmed after order placement.
A10: ="Your Reference"&": "&'Customer Costing'!D1 -> Your Reference: [Input Manually] | G10: • | H10: Delivery Terms: | I10: ='Customer Costing'!F3 -> DAP Bahrain at your store or PH Trading
A11: Dear Sir, We appreciate your interest in our products and thank you for your inquiry. Enclosed, you will find our quotation tailored for your specific application. Our proposal is prepared based on the details and specifications provided by you. | G11: • | H11: Installation | I11: =IF('Customer Costing'!H3="No","Excluded / not in our scope","Check Quotation for pricing") -> Excluded / not in our scope
G12: • | H12: Commissioning | I12: =IF('Customer Costing'!H4="No","Excluded / not in our scope","Check Quotation for pricing") -> Excluded / not in our scope
G13: • | H13: Testing | I13: =IF('Customer Costing'!H5="No","Excluded / not in our scope","Check Quotation for pricing") -> Excluded / not in our scope
G14: • | H14: Test Certificate | I14: =VLOOKUP('Customer Costing'!H1,Code!A40:B42,2,0) -> Additional charges applicable as per OEM terms
G15: • | H15: Certificate of Origin | I15: =VLOOKUP('Customer Costing'!H1,Code!A40:B42,2,0) -> Additional charges applicable as per OEM terms
A16: Sr. No. | B16: Item Description, Order Code* | C16: Unit cost | D16: Qty | E16: Amount (BHD) | G16: • | H16: Country of origin | I16: =VLOOKUP('Customer Costing'!F5,Code!C23:D30,2,0) -> Select Country
A17: 1 | B17: ='PH to AHS'!C$8&CHAR(10)&'PH to AHS'!C$9&CHAR(10)&'PH to AHS'!C$10 -> [Product 1] [Model 1] [Specifiation 1] | C17: ='PH to AHS'!$C$27 -> 712.76 | D17: ='Customer Costing'!C$11 -> 1 | E17: =C17*D17 -> 712.76 | G17: • | H17: Certificate of Conformity | I17: =VLOOKUP('Customer Costing'!H1,Code!A40:B42,2,0) -> Additional charges applicable as per OEM terms
A18: 2 | B18: ='PH to AHS'!D$8&CHAR(10)&'PH to AHS'!D$9&CHAR(10)&'PH to AHS'!D$10 -> [Product 2] [Model 2] [Specifiation 2] | C18: ='PH to AHS'!$D$27 -> 233.81 | D18: ='Customer Costing'!D$11 -> 1 | E18: =C18*D18 -> 233.81 | G18: • | H18: Please check Annexure 1 for detailed Order Code(s)
A19: 3 | B19: ='PH to AHS'!E$8&CHAR(10)&'PH to AHS'!E$9&CHAR(10)&'PH to AHS'!E$10 -> [Product 3] [Model 3] [Specifiation 3] | C19: ='PH to AHS'!$E$27 -> 342.99 | D19: ='Customer Costing'!E$11 -> 1 | E19: =C19*D19 -> 342.99 | G19: • | H19: This proposal is subject to general terms and conditions of delivery and sales as per OEM.
A20: 4 | B20: ='PH to AHS'!F$8&CHAR(10)&'PH to AHS'!F$9&CHAR(10)&'PH to AHS'!F$10 -> [Product 4] [Model 4] [Specifiation 4] | C20: ='PH to AHS'!$F$27 -> 0 | D20: ='Customer Costing'!F$11 -> 0 | E20: =C20*D20 -> 0 | G20: • | H20: We have chosen our instruments according to the specifications given. However, we kindly ask you to thoroughly check the technical data with respect to suitability for your application.
A21: 5 | B21: ='PH to AHS'!G$8&CHAR(10)&'PH to AHS'!G$9&CHAR(10)&'PH to AHS'!G$10 -> [Product 5] [Model 5] [Specifiation 5] | C21: ='PH to AHS'!$G$27 -> 0 | D21: ='Customer Costing'!G$11 -> 0 | E21: =C21*D21 -> 0
A22: 6 | B22: ='PH to AHS'!H$8&CHAR(10)&'PH to AHS'!H$9&CHAR(10)&'PH to AHS'!H$10 -> [Product 6] [Model 6] [Specifiation 6] | C22: ='PH to AHS'!$H$27 -> 0 | D22: ='Customer Costing'!H$11 -> 0 | E22: =C22*D22 -> 0 | H22: This quotation is confidential.
A23: 7 | B23: ='PH to AHS'!I$8&CHAR(10)&'PH to AHS'!I$9&CHAR(10)&'PH to AHS'!I$10 -> [Product 7] [Model 7] [Specifiation 7] | C23: ='PH to AHS'!$I$27 -> 0 | D23: ='Customer Costing'!I$11 -> 0 | E23: =C23*D23 -> 0
A24: 8 | B24: ='PH to AHS'!J$8&CHAR(10)&'PH to AHS'!J$9&CHAR(10)&'PH to AHS'!J$10 -> [Product 8] [Model 8] [Specifiation 8] | C24: ='PH to AHS'!$J$27 -> 0 | D24: ='Customer Costing'!J$11 -> 0 | E24: =C24*D24 -> 0 | H24: Best Regards,
A25: 9 | B25: ='PH to AHS'!K$8&CHAR(10)&'PH to AHS'!K$9&CHAR(10)&'PH to AHS'!K$10 -> [Product 9] [Model 9] [Specifiation 9] | C25: ='PH to AHS'!$K$27 -> 0 | D25: ='Customer Costing'!K$11 -> 0 | E25: =C25*D25 -> 0 | H25: =E7 -> Quote Prepared By
A26: 10 | B26: ='PH to AHS'!L$8&CHAR(10)&'PH to AHS'!L$9&CHAR(10)&'PH to AHS'!L$10 -> [Product 10] [Model 10] [Specifiation 10] | C26: ='PH to AHS'!$L$27 -> 0 | D26: ='Customer Costing'!L$11 -> 0 | E26: =C26*D26 -> 0 | H26: =VLOOKUP(H25,Code!A1:B7,2,0) -> Designation
A27: 11 | B27: ='PH to AHS'!M$8&CHAR(10)&'PH to AHS'!M$9&CHAR(10)&'PH to AHS'!M$10 -> [Product 11] [Model 11] [Specifiation 11] | C27: ='PH to AHS'!$M$27 -> 0 | D27: ='Customer Costing'!M$11 -> 0 | E27: =C27*D27 -> 0 | H27: ="Mob: "&VLOOKUP(H25,Code!A1:D8,3,0) -> Mob: Contact Number
A28: 12 | B28: ='PH to AHS'!N$8&CHAR(10)&'PH to AHS'!N$9&CHAR(10)&'PH to AHS'!N$10 -> [Product 12] [Model 12] [Specifiation 12] | C28: ='PH to AHS'!$N$27 -> 0 | D28: ='Customer Costing'!N$11 -> 0 | E28: =C28*D28 -> 0 | H28: ="Email: "&VLOOKUP(H25,Code!A1:D8,4,0) -> Email: Email
H29: ='PH to AHS'!B1 -> AHS Trading WLL
B30: ='Customer Costing'!R8&CHAR(10)&'Customer Costing'!R9&CHAR(10)&'Customer Costing'!R10 | H30: www.platinumholdings.com.bh
D33: SUBTOTAL | E33: =SUM(E17:E28) -> 1289.56
D34: DISCOUNT | E34: 0
D35: VAT 10% | E35: =(E33+E34)*0.1 -> 128.956
D36: TOTAL (BHD) | E36: =E33-E34+E35 -> 1418.516
H40: Thank you for your business! Should you have any enquiries concerning this quote, Email support@platinumholdings.com.bh
A44: Paste on page 1 | G44: Paste on page 2

Sheet PH to AHS
A1: Division | B1: AHS Trading WLL | C1: RFQ Refference | D1: [Input Manually] | G1: COC and COO | H1: COO/COC Certificates
A2: Date | B2: =TODAY() -> 46097 | C2: Folder Number | E2: Est. Delivery | G2: Test Certificate | H2: Select Certificates
A3: Prepared By | C3: Costing ID | E3: Delivery Terms | G3: Installation | H3: No
A4: Customer | B4: AHS Trading | C4: Contact Person | D4: Choose Contact Person | E4: order Type | G4: Commisioning | H4: No
A5: Reference | B5: Email | C5: Payment Terms | E5: Country of Origin | G5: Testing | H5: No
A7: Supplier | C7: Principle Name | D7: Principle Name | E7: Principle Name | F7: Principle Name | G7: Principle Name | H7: Principle Name | I7: Principle Name | J7: Principle Name | K7: Principle Name | L7: Principle Name | M7: Principle Name | N7: Principle Name | O7: Total for Order
A8: Equipment | C8: [Product 1] | D8: [Product 2] | E8: [Product 3] | F8: [Product 4] | G8: [Product 5] | H8: [Product 6] | I8: [Product 7] | J8: [Product 8] | K8: [Product 9] | L8: [Product 10] | M8: [Product 11] | N8: [Product 12]
A9: Model | C9: [Model 1] | D9: [Model 2] | E9: [Model 3] | F9: [Model 4] | G9: [Model 5] | H9: [Model 6] | I9: [Model 7] | J9: [Model 8] | K9: [Model 9] | L9: [Model 10] | M9: [Model 11] | N9: [Model 12]
A10: Specification / Order Code | C10: [Specifiation 1] | D10: [Specifiation 2] | E10: [Specifiation 3] | F10: [Specifiation 4] | G10: [Specifiation 5] | H10: [Specifiation 6] | I10: [Specifiation 7] | J10: [Specifiation 8] | K10: [Specifiation 9] | L10: [Specifiation 10] | M10: [Specifiation 11] | N10: [Specifiation 12]
A11: Currency | B11: Quantity | C11: 1 | D11: 1 | E11: 1 | F11: 1 | G11: 1 | H11: 1 | I11: 1 | J11: 1 | K11: 1 | L11: 1 | M11: 1 | N11: 1
A12: EUR | B12: FOB | O12: =SUM(C12:N12) -> 0
A13: EUR | B13: Freight | C13: =C12*0.09 -> 0 | D13: =D12*0.09 -> 0 | E13: =E12*0.09 -> 0 | F13: =F12*0.09 -> 0 | G13: =G12*0.09 -> 0 | H13: =H12*0.09 -> 0 | I13: =I12*0.09 -> 0 | J13: =J12*0.09 -> 0 | ... N13: =N12*0.09 -> 0 | O13: =SUM(C13:N13) -> 0
B14: Exchange Rate to BHD | C14: =IF($A$12="EUR",0.45,0.39) -> 0.45 | D14: =IF($A$12="EUR",0.45,0.39) -> 0.45 | E14: =IF($A$12="EUR",0.45,0.39) -> 0.45 | F14: =IF($A$12="EUR",0.45,0.39) -> 0.45 | G14: =IF($A$12="EUR",0.45,0.39) -> 0.45 | H14: =IF($A$12="EUR",0.45,0.39) -> 0.45 | I14: =IF($A$12="EUR",0.45,0.39) -> 0.45 | J14: =IF($A$12="EUR",0.45,0.39) -> 0.45 | ... N14: =IF($A$12="EUR",0.45,0.39) -> 0.45
A15: BHD | B15: FOB | C15: =C12*C14 -> 0 | D15: =D12*D14 -> 0 | E15: =E12*E14 -> 0 | F15: =F12*F14 -> 0 | G15: =G12*G14 -> 0 | H15: =H12*H14 -> 0 | I15: =I12*I14 -> 0 | J15: =J12*J14 -> 0 | ... N15: =N12*N14 -> 0 | O15: =SUM(C15:N15) -> 0
A16: BHD | B16: Freight | C16: =C13*C14 -> 0 | D16: =D13*D14 -> 0 | E16: =E13*E14 -> 0 | F16: =F13*F14 -> 0 | G16: =G13*G14 -> 0 | H16: =H13*H14 -> 0 | I16: =I13*I14 -> 0 | J16: =J13*J14 -> 0 | ... N16: =N13*N14 -> 0 | O16: =SUM(C16:N16) -> 0
B17: C&F | C17: =C15+C16 -> 0 | D17: =D15+D16 -> 0 | E17: =E15+E16 -> 0 | F17: =F15+F16 -> 0 | G17: =G15+G16 -> 0 | H17: =H15+H16 -> 0 | I17: =I15+I16 -> 0 | J17: =J15+J16 -> 0 | ... N17: =N15+N16 -> 0 | O17: =SUM(C17:N17) -> 0
B18: Insurance | C18: 0 | D18: 0 | E18: 0 | F18: 0 | G18: 0 | H18: 0 | I18: 0 | J18: 0 | K18: 0 | L18: 0 | M18: 0 | N18: 0 | O18: =SUM(C18:N18) -> 0
A19: 0.06 | B19: Customs @ 6% | C19: =C17*$A$19 -> 0 | D19: =D17*$A$19 -> 0 | E19: =E17*$A$19 -> 0 | F19: =F17*$A$19 -> 0 | G19: =G17*$A$19 -> 0 | H19: =H17*$A$19 -> 0 | I19: =I17*$A$19 -> 0 | J19: =J17*$A$19 -> 0 | ... N19: =N17*$A$19 -> 0 | O19: =SUM(C19:N19) -> 0
B20: Landed Cost | C20: =SUM(C17:C19) -> 0 | D20: =SUM(D17:D19) -> 0 | E20: =SUM(E17:E19) -> 0 | F20: =SUM(F17:F19) -> 0 | G20: =SUM(G17:G19) -> 0 | H20: =SUM(H17:H19) -> 0 | I20: =SUM(I17:I19) -> 0 | J20: =SUM(J17:J19) -> 0 | ... N20: =SUM(N17:N19) -> 0 | O20: =SUM(C20:N20) -> 0
A21: 0.04 | B21: Handling @ 4% | C21: =C20*$A$21 -> 0 | D21: =D20*$A$21 -> 0 | E21: =E20*$A$21 -> 0 | F21: =F20*$A$21 -> 0 | G21: =G20*$A$21 -> 0 | H21: =H20*$A$21 -> 0 | I21: =I20*$A$21 -> 0 | J21: =J20*$A$21 -> 0 | ... N21: =N20*$A$21 -> 0 | O21: =SUM(C21:N21) -> 0
A22: 0.01 | B22: Finance Charges @1% | C22: =C20*$A$22 -> 0 | D22: =D20*$A$22 -> 0 | E22: =E20*$A$22 -> 0 | F22: =F20*$A$22 -> 0 | G22: =G20*$A$22 -> 0 | H22: =H20*$A$22 -> 0 | I22: =I20*$A$22 -> 0 | J22: =J20*$A$22 -> 0 | ... N22: =N20*$A$22 -> 0 | O22: =SUM(C22:N22) -> 0
B23: Other Costs | C23: 0 | D23: 0 | E23: 0 | F23: 0 | G23: 0 | H23: 0 | I23: 0 | J23: 0 | K23: 0 | L23: 0 | M23: 0 | N23: 0 | O23: =SUM(C23:N23) -> 0
B24: Total Cost | C24: ='Customer Costing'!C31 -> 692 | D24: ='Customer Costing'!D31 -> 227 | E24: ='Customer Costing'!E31 -> 333 | F24: ='Customer Costing'!F31 -> 0 | G24: ='Customer Costing'!G31 -> 0 | H24: ='Customer Costing'!H31 -> 0 | I24: ='Customer Costing'!I31 -> 0 | J24: ='Customer Costing'!J31 -> 0 | ... N24: ='Customer Costing'!N31 -> 0 | O24: =SUM(C24*C11,D24*D11,E24*E11,F24*F11,G24*G11,H24*H11,I24*I11,J24*J11,K24*K11,L24*L11,M24*M11,N24*N11) -> 1252
A25: 0.03 | B25: Markup @ 20% | C25: =C24*$A$25 -> 20.76 | D25: =D24*$A$25 -> 6.81 | E25: =E24*$A$25 -> 9.99 | F25: =F24*$A$25 -> 0 | G25: =G24*$A$25 -> 0 | H25: =H24*$A$25 -> 0 | I25: =I24*$A$25 -> 0 | J25: =J24*$A$25 -> 0 | ... N25: =N24*$A$25 -> 0 | O25: =SUM(C25:N25) -> 37.56
A26: Selling Price | C26: =C24+C25 -> 712.76 | D26: =D24+D25 -> 233.81 | E26: =E24+E25 -> 342.99 | F26: =F24+F25 -> 0 | G26: =G24+G25 -> 0 | H26: =H24+H25 -> 0 | I26: =I24+I25 -> 0 | J26: =J24+J25 -> 0 | ... N26: =N24+N25 -> 0 | O26: =SUM(C26:N26) -> 1289.56
A27: Suggested Price per unit | C27: =C26 -> 712.76 | D27: =D26 -> 233.81 | E27: =E26 -> 342.99 | F27: =F26 -> 0 | G27: =G26 -> 0 | H27: =H26 -> 0 | I27: =I26 -> 0 | J27: =J26 -> 0 | ... N27: =N26 -> 0 | O27: =SUM(C27:N27) -> 1289.56
A28: Total Suggested Price | C28: =C27*C11 -> 712.76 | D28: =D27*D11 -> 233.81 | E28: =E27*E11 -> 342.99 | F28: =F27*F11 -> 0 | G28: =G27*G11 -> 0 | H28: =H27*H11 -> 0 | I28: =I27*I11 -> 0 | J28: =J27*J11 -> 0 | ... N28: =N27*N11 -> 0 | O28: =SUM(C28:N28) -> 1289.56
O29: =O28*10% -> 128.956 | P29: VAT (10%)
O30: =O28+O29 -> 1418.516 | P30: Grand Total
A31: Summary | C31: Total | D31: VAT | E31: Total with VAT
A32: Total PO value expected from Client | C32: =O28 -> 1289.56 | D32: =C32*0.1 -> 128.956 | E32: =C32+D32 -> 1418.516
A33: PH TRADING COST | C33: =O24 -> 1252 | D33: =C33*0.1 -> 125.2 | E33: =C33+D33 -> 1377.2
A34: Profit | C34: =C32-C33 -> 37.56 | D34: =D32-D33 -> 3.756 | E34: =E32-E33 -> 41.316
B35: Profit % | C35: =(C32-C33)/C33 -> 0.03

Sheet Code
A1: Quote Prepared By | B1: Designation | C1: Contact Number | D1: Email | H1: Customer ID Generator | M1: Customer Segment | N1: Short Code
A2: Stanley Vaz | B2: COO | C2: +973 3662 3662 | D2: stanley.vaz@platinumholdings.com.bh | G2: Business Account Name | H2: Customer Type | I2: Short Code | J2: Serial No. | K2: CID | M2: Consultant | N2: CO
A3: Abhie Kore | B3: Business Head | C3: +973 3677 1513 | D3: abhi.kore@platinumholdings.com.bh | G3: L&T TECHNOLOGY SERVICES | H3: Consultant | I3: CO | J3: 1 | K3: =I3&J3 -> CO1 | M3: End Customer | N3: EC
A4: V.M. Sundar | B4: Manager | C4: +973 3826 0157 | D4: vm.sundar@platinumholdings.com.bh | G4: Mott MacDonald | H4: Consultant | I4: CO | J4: 2 | K4: =I4&J4 -> CO2 | M4: Engineering Company, EPC/Licensor | N4: EP
A5: Ebin Chacko | B5: Technical Sales Engineer | C5: +973 3641 8072 | D5: ebin.chacko@platinumholdings.com.bh | G5: SSH | H5: Consultant | I5: CO | J5: 3 | K5: =I5&J5 -> CO3 | M5: International Reseller | N5: IR
A6: Periyasamy N | B6: Technical Sales Engineer | G6: STANLAB BUSINESS CONSULTANCY | H6: Consultant | I6: CO | J6: 4 | K6: =I6&J6 -> CO4 | M6: Machine Builder, Skid Manufacturer | N6: MB
A7: Ramya Baskaran | B7: Sales Support | C7: +973 3889 0513 | D7: support@platinumholdings.com.bh | G7: Stantec-Khonji | H7: Consultant | I7: CO | J7: 5 | K7: =I7&J7 -> CO5 | M7: National Reseller | N7: NR
G8: Tebodin Middle East Ltd. | H8: Consultant | I8: CO | J8: 6 | K8: =I8&J8 -> CO6 | M8: OEM | N8: OM
G9: AGAS International | H9: End Customer | I9: EC | J9: 1 | K9: =I9&J9 -> EC1 | M9: PH Trading | N9: PH
G10: Ahmadi industries | H10: End Customer | I10: EC | J10: 2 | K10: =I10&J10 -> EC2 | M10: Plant Builder | N10: PB
G11: Ahmedi industries | H11: End Customer | I11: EC | J11: 3 | K11: =I11&J11 -> EC3 | M11: Service Provider, Service Company | N11: SP
G12: Air Liquide Bahrain | H12: End Customer | I12: EC | J12: 4 | K12: =I12&J12 -> EC4 | M12: System Integrator | N12: SI
G13: Al Alawi | H13: End Customer | I13: EC | J13: 5 | K13: =I13&J13 -> EC5
A14: Select payment terms | B14: Select Delivery terms | C14: Select Est Delivery | D14: Select Warranty | G14: al eradah chemical bahrain | H14: End Customer | I14: EC | J14: 6 | K14: =I14&J14 -> EC6
A15: 100% Advance Payment with PO | B15: DAP Bahrain at your store or PH Trading | C15: 3-5 weeks | D15: Against Manufacturing Defects (12 months from the date of delivery ) | G15: Al Ezzel Engie O&M Co. W.L.L | H15: End Customer | I15: EC | J15: 7 | K15: =I15&J15 -> EC7
A16: 100% Payment Against Delivery | B16: Ex-Works (EXW) | C16: 4-6 weeks | D16: No warranty for spare parts | G16: Al Ezzel O&M Co. W.L.L | H16: End Customer | I16: EC | J16: 8 | K16: =I16&J16 -> EC8
A17: 30 days from Date of Delivery | B17: Free Carrier (FCA) | C17: 5-7 weeks | G17: Al Madar General trading | H17: End Customer | I17: EC | J17: 9 | K17: =I17&J17 -> EC9
A18: 60 days from Date of Delivery | B18: Delivered Duty Paid (DDP) | C18: 7-9 weeks | G18: Al Manhal Water Factory | H18: End Customer | I18: EC | J18: 10 | K18: =I18&J18 -> EC10
A19: Letter of Credit (LC) | C19: 9-11 weeks | G19: Al Sane & Partners Soft drinks | H19: End Customer | I19: EC | J19: 11 | K19: =I19&J19 -> EC11
A20: Project Stage Payments | C20: 12-14 weeks | G20: Al-Awadi Factory | H20: End Customer | I20: EC | J20: 12 | K20: =I20&J20 -> EC12
A21: 50% Advance + 50% Against Delivery | C21: 16-18 weeks | G21: ALEASTUR MIDDLE EAST W.L.L | H21: End Customer | I21: EC | J21: 13 | K21: =I21&J21 -> EC13
C22: To be Known after order is placed | G22: ALUMINIUM BAHRAIN B.S.C.(C) | H22: End Customer | I22: EC | J22: 14 | K22: =I22&J22 -> EC14
C23: Country of Origin | D23: Select Country | G23: AluServ Middle East W.L.L | H23: End Customer | I23: EC | J23: 15 | K23: =I23&J23 -> EC15
A24: Select order type | C24: DE | D24: Germany | G24: Aman Water | H24: OEM, Machine and Skid Builder | I24: EC | J24: 16 | K24: =I24&J24 -> EC16
A25: General | C25: CH | D25: Switzerland | G25: Aqua Seef | H25: End Customer | I25: EC | J25: 17 | K25: =I25&J25 -> EC17
A26: Spareparts | C26: FR | D26: France | G26: Aqua TT | H26: End Customer | I26: EC | J26: 18 | K26: =I26&J26 -> EC18
A27: Items + Spareparts | C27: UK | D27: United Kingdom (GB) | G27: Arab. Gulf Cement Co.. | H27: End Customer | I27: EC | J27: 19 | K27: =I27&J27 -> EC19
C28: US | D28: United States of America | G28: Arab. Sugar Co. B.S.C | H28: End Customer | I28: EC | J28: 20 | K28: =I28&J28 -> EC20
C29: SL | D29: Slovenia | G29: Arabian Gulf Cement Co. Wll | H29: End Customer | I29: EC | J29: 21 | K29: =I29&J29 -> EC21
A30: Principle Name | B30: Statement | C30: GR | D30: Greece | G30: Arla Foods Bahrain S.P.C | H30: End Customer | I30: EC | J30: 22 | K30: =I30&J30 -> EC22
A31: EH | B31: (Authorized Endress Hauser Agency in Bahrain) | C31: IT | D31: Italy | G31: Awal Dairy - Tetrapack | H31: End Customer | I31: EC | J31: 23 | K31: =I31&J31 -> EC23
A32: GI | B32: (Authorized GIC & Guages Bourdon Agency in Bahrain) | G32: Awal Dairy Co. WLL | H32: End Customer | I32: EC | J32: 24 | K32: =I32&J32 -> EC24
A33: SM | B33: (Authorized Servomex Agency in Bahrain) | G33: Bahrain LNG W.L.L | H33: End Customer | I33: EC | J33: 25 | K33: =I33&J33 -> EC25
A34: LG | B34: (Authorized landys+Gyr Agency in Bahrain) | G34: Bahrain LNG/ Seapeak | H34: End Customer | I34: EC | J34: 26 | K34: =I34&J34 -> EC26
A35: IS | B35: (Authorized Iskraemeco Agency in Bahrain) | G35: Bahrain Medical | H35: End Customer | I35: EC | J35: 27 | K35: =I35&J35 -> EC27
G36: Bahrain National Gas Company | H36: End Customer | I36: EC | J36: 28 | K36: =I36&J36 -> EC28
G37: Bahrain Pharma | H37: End Customer | I37: EC | J37: 29 | K37: =I37&J37 -> EC29
G38: Bahrain Steel BSCC (E.C.) - Sulb | H38: End Customer | I38: EC | J38: 30 | K38: =I38&J38 -> EC30
G39: Bahrain Sugar Refinery | H39: End Customer | I39: EC | J39: 31 | K39: =I39&J39 -> EC31
A40: COO/COC Certificates | B40: Select Certificates | G40: BALEXCO | H40: End Customer | I40: EC | J40: 32 | K40: =I40&J40 -> EC32
A41: Yes | B41: Included | G41: BANAGAS | H41: End Customer | I41: EC | J41: 33 | K41: =I41&J41 -> EC33
A42: No | B42: Additional charges applicable as per OEM terms | G42: Bapco refining | H42: End Customer | I42: EC | J42: 34 | K42: =I42&J42 -> EC34
G43: BAPCO UPSTREAM W.L.L | H43: End Customer | I43: EC | J43: 35 | K43: =I43&J43 -> EC35
G44: BASF - The chemical Company | H44: End Customer | I44: EC | J44: 36 | K44: =I44&J44 -> EC36
G45: Batelco | H45: End Customer | I45: EC | J45: 37 | K45: =I45&J45 -> EC37
G46: BJFCO | H46: End Customer | I46: EC | J46: 38 | K46: =I46&J46 -> EC38
G47: Contax Partners | H47: End Customer | I47: EC | J47: 39 | K47: =I47&J47 -> EC39
G48: CPIC Abahsain Fiberglass WLL | H48: End Customer | I48: EC | J48: 40 | K48: =I48&J48 -> EC40
G49: CPIC fiber glass | H49: End Customer | I49: EC | J49: 41 | K49: =I49&J49 -> EC41
G50: CROWN PLAZA | H50: End Customer | I50: EC | J50: 42 | K50: =I50&J50 -> EC42
G51: Dalkia Utilities Co. W.L.L | H51: End Customer | I51: EC | J51: 43 | K51: =I51&J51 -> EC43
G52: Diyar - Eagle Hills | H52: End Customer | I52: EC | J52: 44 | K52: =I52&J52 -> EC44
G53: Eltekon Oil & Gas | H53: OEM, Machine and Skid Builder | I53: EC | J53: 45 | K53: =I53&J53 -> EC45
G54: Energy Central | H54: End Customer | I54: EC | J54: 46 | K54: =I54&J54 -> EC46
... G154: Zohal Construction Company W.L.L. | H154: Engineering Company, EPC/Licensor | I154: EP | J154: 36 | K154: =I154&J154 -> EP36
G155: AEMCO | H155: Engineering Company, EPC/Licensor | J155: 38 | K155: EP38
G156: Howdaj | H156: International Reseller | I156: IR | J156: 1 | K156: =I156&J156 -> IR1
G157: PETRO TECHNOLOGY SUPPLIES CO WLL | H157: International Reseller | I157: IR | J157: 2 | K157: =I157&J157 -> IR2
G158: Theia New Consultancy W.L.L. | H158: International Reseller | I158: IR | J158: 3 | K158: =I158&J158 -> IR3
G159: Flowlead | H159: Machine Builder, Skid Manufacturer | I159: MB | J159: 1 | K159: =I159&J159 -> MB1
G160: Abraqyah Trading Company | H160: National Reseller | I160: NR | J160: 1 | K160: =I160&J160 -> NR1
G161: Al Bakali | H161: National Reseller | I161: NR | J161: 2 | K161: =I161&J161 -> NR2
G162: Al Bakali Geneal Trading B.S.C. | H162: National Reseller | I162: NR | J162: 3 | K162: =I162&J162 -> NR3
G163: Al Hilal Group | H163: National Reseller | I163: NR | J163: 4 | K163: =I163&J163 -> NR4
G164: AL HILLO trading CO W.L.L, | H164: National Reseller | I164: NR | J164: 5 | K164: =I164&J164 -> NR5
G165: AL HILLO Trdg CO W.L.L, | H165: National Reseller | I165: NR | J165: 6 | K165: =I165&J165 -> NR6
G166: AL HOSN TRADING | H166: National Reseller | I166: NR | J166: 7 | K166: =I166&J166 -> NR7
G167: Al Rawaby trading CO | H167: National Reseller | I167: NR | J167: 8 | K167: =I167&J167 -> NR8
... G255: WestPoint Home (Bahrain) W.L.L | H255: National Reseller | I255: NR | J255: 96 | K255: =I255&J255 -> NR96
G256: AHS Trading | H256: National Reseller | I256: NR | J256: 97 | K256: NR97
G257: :XENIT TECHNOLOGY SOLUTIONS W.L.L | H257: National Reseller | I257: NR | J257: 98 | K257: NR98
G258: Arabian International Contracting | H258: Plant Builder | I258: PB | J258: 1 | K258: =I258&J258 -> PB1
G259: Flora Contracting and Maintenance | H259: Plant Builder | I259: PB | J259: 2 | K259: =I259&J259 -> PB2
G260: Silver Fils International Co WLL | H260: Plant Builder | I260: PB | J260: 3 | K260: =I260&J260 -> PB3
G261: SOCIETE INTERNATIONALE DE | H261: Plant Builder | I261: PB | J261: 4 | K261: =I261&J261 -> PB4
G262: P H Trading W.L.L | H262: PH Trading | I262: PH | J262: 1 | K262: =I262&J262 -> PH1
G263: Acadia Solutions WLL | H263: System Integrator | I263: SI | J263: 1 | K263: =I263&J263 -> SI1
G264: Al Moayyed air conditioning | H264: System Integrator | I264: SI | J264: 2 | K264: =I264&J264 -> SI2
G265: Almoayyed | H265: System Integrator | I265: SI | J265: 3 | K265: =I265&J265 -> SI3
G266: Anasia Trading Co. Ltd. | H266: System Integrator | I266: SI | J266: 4 | K266: =I266&J266 -> SI4
G267: AQUA TECHNOLOGY TRANSFER W.L.L. | H267: System Integrator | I267: SI | J267: 5 | K267: =I267&J267 -> SI5
G268: Arrowfinch | H268: System Integrator | I268: SI | J268: 6 | K268: =I268&J268 -> SI6
G269: ARROWFINCH TECHNOLOGIES WLL | H269: System Integrator | I269: SI | J269: 7 | K269: =I269&J269 -> SI7
... G312: Worley Solutions Bahrain S.P.C | H312: Service Provider, Service Company | I312: SP | J312: 17 | K312: =I312&J312 -> SP17
G313: Nass Electrical Contracting | H313: Engineering Company, EPC/Licensor | I313: EP | J313: 37 | K313: EP37
G314: Al Faris Industrial supplies | H314: Service Provider, Service Company | I314: SP | J314: 18 | K314: SP18
G315: Al Mufeed Electrical Services W.L.L | H315: Engineering Company | I315: SP | J315: 38 | K315: EP38
G316: Abu Obaid Cont & Trading Group W.L.L | H316: Service Provider, Service Company | I316: SP | J316: 19 | K316: SP19
G317: JAHECON W.L.L | H317: System Integrator | I317: SI | J317: 34 | K317: SI34

Sheet Customer Database
A1: Choose Contact Person | B1: Salutation | C1: Phone | D1: Email | E1: Address | F1: Business Account Name | G1: Customer Type
A2: Mohammed Ali | B2: Mr. | C2: 66720555 | D2: m.ali@abraqyah.com | E2: Office No. 105, Building No. 106, Road No. 20, Block No. 331, Bu Ghazal, Kingdom of Bahrain. | F2: Abraqyah Trading Company | G2: National Reseller
A3: Vignesh Ganesan | B3: Mr. | C3: 39623555 | D3: vignesh@abraqyah.com | E3: Office No. 105, Building No. 106, Road No. 20, Block No. 331, Bu Ghazal, Kingdom of Bahrain. | F3: Abraqyah Trading Company | G3: National Reseller
A4: Saifudheen Ahmmed | B4: Mr. | C4: 36596976 | D4: sales@acadiamea.com | E4: 1336 Block 713 Street 1326 Tubli, Al Asimah, Bahrain. | F4: Acadia Solutions WLL | G4: System Integrator
A5: Dennis Hmelev | B5: Mr. | C5: +97333549523 | D5: info@agalpro.com | E5: Hidd, Kingdom of Bahrain | F5: Agalpro Solutions | G5: Service Provider, Service Company
A6: Jagadessan bat | B6: Mr. | C6: 39133429 | D6: jagadeesan@agasintl.com | E6: P.O. Box 15360, Kingdom of Bahrain. Phone: +973 17822240. | F6: AGAS International | G6: End Customer
A7: Nadarajan Padmanabhan | B7: Mr. | C7: 1783 0495 | D7: info@agasintl.com | E7: P.O. Box 15360, Kingdom of Bahrain. Phone: +973 17822240. | F7: AGAS International | G7: End Customer
A8: Devidas Daundkar | B8: Mr. | C8: 34660736 | D8: devidas.d@ahmadi.com | E8: Post Box 34, Road 2913, Building 665, Block 329, Manama, Bahrain | F8: Ahmadi industries | G8: End Customer
A9: SASIKUMAR | B9: Mr. | C9: 1726 5444 | D9: admin@ahmadipepsi.com | E9: Post Box 34, Road 2913, Building 665, Block 329, Manama, Bahrain | F9: Ahmadi industries | G9: End Customer
A10: P Saravanan | B10: Mr. | C10: 17708200 | D10: saravanan@airliquide.com | E10: Building 1398, 4626 R 1702, Manama, Manama | F10: Air Liquide Bahrain | G10: End Customer
A11: Basil N. Maduakor | B11: Mr. | C11: (0)66398838 | D11: parker@al-alawi.com | E11: 307 Block 363 Street 328 Shaikh Salman Highway, Bilad Al Qadeem, Al Asimah | F11: Al Alawi | G11: End Customer
A12: Hussain Al Bakali | B12: Mr. | C12: 17551189 | D12: albakali@albakali.net | E12: Ajeyaad Tower, Building No 2304 2830 Road 2831, MANAMA | F12: Al Bakali Geneal Trading B.S.C. | G12: National Reseller
A13: jithin V tom | B13: Mr. | C13: 32010832 | D13: info@aleradahchemicals.com | E13: Rd No 310, Madinat Hamad, Bahrain | F13: al eradah chemical bahrain | G13: End Customer
A14: Adi kesavan | B14: Mr. | C14: 33234396 | D14: adi.kesavan@alezzelom.com | E14: Flat 3, Building 285, Block 115, Al Hidd, Bahrain | F14: Al Ezzel O&M Co. W.L.L | G14: End Customer | H14: 30 days
A15: Ali Moosa Jaffar | B15: Mr. | D15: ali.moosa@alezzelom.com | E15: Flat 3, Building 285, Block 115, Al Hidd, Bahrain | F15: Al Ezzel O&M Co. W.L.L | G15: End Customer | H15: 30 days
A16: Balachandra poojari | B16: Mr. | C16: 33444105 | D16: balachandar.poojari@alezzelom.com | E16: Flat 3, Building 285, Block 115, Al Hidd, Bahrain | F16: Al Ezzel O&M Co. W.L.L | G16: End Customer | H16: 30 days
A17: Jayaprakash Poojary | B17: Mr. | C17: +973 35105035 | D17: jayaprakash.poojary@engie.com | E17: Flat 3, Building 285, Block 115, Al Hidd, Bahrain | F17: Al Ezzel O&M Co. W.L.L | G17: End Customer | H17: 30 days
A18: Koteswara rao | B18: Mr. | C18: 33017070 | D18: vithanala.rao@alezzelom.com | E18: Flat 3, Building 285, Block 115, Al Hidd, Bahrain | F18: Al Ezzel O&M Co. W.L.L | G18: End Customer | H18: 30 days
A19: Nazeer Khan | B19: Mr. | C19: +973 37766854 | D19: nazeer.khan@engie.com | E19: Flat 3, Building 285, Block 115, Al Hidd, Bahrain | F19: Al Ezzel O&M Co. W.L.L | G19: End Customer | H19: 30 days
A20: Nazeer mohammed Khan | B20: Mr. | C20: 37766854 | D20: nazeer.khan@alezzelom.com | E20: Flat 3, Building 285, Block 115, Al Hidd, Bahrain | F20: Al Ezzel O&M Co. W.L.L | G20: End Customer | H20: 30 days
A21: Qasim Maqbool | B21: Mr. | D21: qasim.maqbool@alezzelom.com | E21: Flat 3, Building 285, Block 115, Al Hidd, Bahrain | F21: Al Ezzel O&M Co. W.L.L | G21: End Customer | H21: 30 days
A22: Venkat rajian.s | B22: Mr. | C22: 39759406 | D22: venkat.rajan@alezzelom.com | E22: Flat 3, Building 285, Block 115, Al Hidd, Bahrain | F22: Al Ezzel O&M Co. W.L.L | G22: End Customer | H22: 30 days
A23: Zahra Alhaddad | B23: Ms. | C23: +973 17844344 | D23: zahra.alhaddad@engie.com | E23: Flat 3, Building 285, Block 115, Al Hidd, Bahrain | F23: Al Ezzel O&M Co. W.L.L | G23: End Customer | H23: 30 days
A24: Jaffar Shoala | B24: Mr. | D24: jaffar.shoala@tradearabia.net | E24: Office 31, Building Road 18, Block 320, Al Hoora, Manama, Bahrain | F24: Al Hilal Group | G24: National Reseller
A25: A.K BABU | B25: Mr. | C25: 39941495 | D25: alhillo@batelco.com.bh | E25: Building B 1030, Flat 12, Block 939, Road 3923, East Riffa, Bahrain | F25: AL HILLO trading CO W.L.L, | G25: National Reseller
A26: mohammed Jaffer | B26: Mr. | D26: mohd.jaffer@alhosntrading.com | E26: 2126 Block 115, Street 1529, Al Hadd, Muharraq, Bahrain | F26: AL HOSN TRADING | G26: National Reseller
A27: Sridhar Shankar | B27: Mr. | C27: 38700406 | D27: sridhar@alhotybahrain.com | E27: Mina Salman, Kingdom of Bahrain | F27: Al Hoty Analytical Services | G27: Service Provider, Service Company
A28: Mugesh Dhason | B28: Mr. | C28: +97335189685 | D28: dmugesh2000@gmail.com | E28: Askar, Kingdom of Bahrain | F28: Al Kooheji Technical Services | G28: Service Provider, Service Company
A29: Joji P. John | B29: Mr. | C29: 39 905548 | D29: almadar2@batelco.com.bh | E29: Near Bahrain Finance, Building 7, Office 1, 8 Road 2831, Salmabad | F29: Al Madar General trading | G29: End Customer
A30: Khaled Al-Bitar | B30: Mr. | C30: 17404435 | D30: info@bh.nestle-waters.com | E30: Road 1161, Building 1493, AL MUSALLA | F30: Al Manhal Water Factory | G30: End Customer
A31: Nahas P Salim | B31: Mr. | C31: +973 33040598 | D31: nahas.s@almoayyedcg.com | E31: Tashan, Manama, Manama, 32232 | F31: Al Moayyed air conditioning | G31: System Integrator
A32: Mohammed Ali | B32: Mr. | C32: +973 - 17830433 | D32: alrawaby@batelco.com.bh | E32: Building 1311, Road 5136, Askar 951, MANAMA | F32: Al Rawaby trading CO | G32: National Reseller
A33: Fahim Abdulla | B33: Mr. | C33: 17728133 | D33: alsane@batelco.com.bh | E33: Building 529, Road 4311, MANAMA, Al-Janubiyah | F33: Al Sane & Partners Soft drinks | G33: End Customer
A34: Manu Manu K Jose | B34: Mr. | C34: 33-647-653 | D34: projects@althawadigroup.com | E34: East Riffa, Kingdom of Bahrain | F34: AL THAWADI | G34: Service Provider, Service Company
A35: Biju YOHANNAN | B35: Mr. | C35: +973-17-291636 | D35: biju.yohannan@alzamih.com | F35: Al Zamih trading & Industrial Supplies | G35: National Reseller
A36: Nishaf Nishaf | B36: Mr. | C36: 38073505 | D36: nishaf@alzamih.com | F36: Al Zamih trading & Industrial Supplies | G36: National Reseller
A37: Saju Abraham | B37: Mr. | D37: enquiry-bh@alzamih.com | F37: Al Zamih trading & Industrial Supplies | G37: National Reseller
A38: Victor Victor | B38: Mr. | C38: (0)17230939 | D38: infoalamantc@gmail.com | E38: Building No. 1564, Hamad Town, Northern Governorate, Bahrain. | F38: ALAMAN trading CO. W.L.L. | G38: National Reseller
A39: Relton Rodrigues | B39: Mr. | C39: 33626462 | D39: relton@alashiqa.com | E39: Flat 12, Building 2300, Road 439, Block 704, Salmabad, Isa Town, Kingdom of Bahrain. | F39: Alashiqa General trading | G39: National Reseller
A40: Sayed Kadam | B40: Mr. | D40: sayeed@alashiqa.com | E40: Flat 12, Building 2300, Road 439, Block 704, Salmabad, Isa Town, Kingdom of Bahrain. | F40: Alashiqa General trading | G40: National Reseller
A41: Faisal Alawadi | B41: Mr. | C41: 33624450 / 966543996972 | D41: faisal@alawadyfactories.com | E41: Hidd, Kingdom of Bahrain | F41: Al-Awadi Factory | G41: End Customer
A42: Enrique Sela | B42: Mr. | C42: +973 3552 5018 | D42: enrique.sela@aleasturme.com | E42: ASKAR, Kingdom of Bahrain | F42: ALEASTUR MIDDLE EAST W.L.L | G42: End Customer
A43: Fahad Mushtaq | B43: Mr. | C43: 17490796 | D43: industrial@alfaris.biz | E43: Riffa, Kingdom of Bahrain | F43: AL-FARIS Industrial Supplies W.L.L | G43: National Reseller
A44: Jino Jose | B44: Mr. | C44: 36998148 | D44: alkomed@batelco.com.bh | E44: MANAMA, Kingdom of Bahrain | F44: ALKOMED | G44: Engineering Company, EPC/Licensor
A45: DEEPESH AMBUJAN | B45: Mr. | C45: 3665 8509 | D45: deepesh@allvoltbh.com | E45: TUBLI, Kingdom of Bahrain | F45: ALL VOLT TRADING | G45: National Reseller
A46: Ashutosh pratap singh | B46: Mr. | C46: 39635480 | D46: ashutosh@almoayyedintl.com | E46: Ma'ameer 635, Kingdom of Bahrain | F46: Almoayyed Electrical & Inst | G46: Engineering Company, EPC/Licensor
A47: Asif Noordeen | B47: Mr. | C47: 39970432 | D47: asifn@almoayyedintl.com.bh | E47: Ma'ameer 635, Kingdom of Bahrain | F47: Almoayyed Electrical & Inst | G47: Engineering Company, EPC/Licensor
A48: Chandramohan Raju | B48: Mr. | C48: 36020233 | D48: chandra.m@almoayyedintl.com.bh | E48: Ma'ameer 635, Kingdom of Bahrain | F48: Almoayyed Electrical & Inst | G48: Engineering Company, EPC/Licensor
A49: Dineshprasad Rai | B49: Mr. | C49: 38201985 | D49: dinesh@almoayyedintl.com.bh | E49: Ma'ameer 635, Kingdom of Bahrain | F49: Almoayyed Electrical & Inst | G49: Engineering Company, EPC/Licensor
A50: Faraz Shaikh | B50: Mr. | C50: 39440131 | D50: faraz@almoayyedintl.com.bh | E50: Ma'ameer 635, Kingdom of Bahrain | F50: Almoayyed Electrical & Inst | G50: Engineering Company, EPC/Licensor
A51: Mohammed Ehtesham Uddin | B51: Mr. | C51: 39642251 | D51: mehtesham@almoayyedintl.com.bh | E51: Ma'ameer 635, Kingdom of Bahrain | F51: Almoayyed Electrical & Inst | G51: Engineering Company, EPC/Licensor
A52: Serin Sam | B52: Mr. | C52: 17700777 | D52: serin@almoayyedintl.com.bh | E52: Ma'ameer 635, Kingdom of Bahrain | F52: Almoayyed Electrical & Inst | G52: Engineering Company, EPC/Licensor
... A66: Charlie S | B66: Mr. | C66: 39218112 | D66: s.charlie@alba.com.bh | E66: Building 15, Road 94, Block 951, King Hamad Highway, Askar, Manama, P.O. Box 57, Kingdom of Bahrain. | F66: ALUMINIUM BAHRAIN B.S.C.(C) | G66: End Customer
A67: Hamad Jahangeer Hatem | B67: Mr. | D67: hamad.jahangeer@alba.com.bh | E67: Building 15, Road 94, Block 951, King Hamad Highway, Askar, Manama, P.O. Box 57, Kingdom of Bahrain. | F67: ALUMINIUM BAHRAIN B.S.C.(C) | G67: End Customer
A68: Hatem Abbas | B68: Mr. | C68: 39788339 | D68: hatem.abbas@alba.com.bh | E68: Building 15, Road 94, Block 951, King Hamad Highway, Askar, Manama, P.O. Box 57, Kingdom of Bahrain. | F68: ALUMINIUM BAHRAIN B.S.C.(C) | G68: End Customer
A69: Hesham aliaskar | B69: Mr. | C69: 1783 0000 | D69: hesham.aliaskar@alba.com.bh | E69: Building 15, Road 94, Block 951, King Hamad Highway, Askar, Manama, P.O. Box 57, Kingdom of Bahrain. | F69: ALUMINIUM BAHRAIN B.S.C.(C) | G69: End Customer
A70: Jaber Ebrahim Mohd | B70: Mr. | C70: 1783 0000 | D70: jaber.ebrahim@alba.com.bh | E70: Building 15, Road 94, Block 951, King Hamad Highway, Askar, Manama, P.O. Box 57, Kingdom of Bahrain. | F70: ALUMINIUM BAHRAIN B.S.C.(C) | G70: End Customer
A71: Kasinathan PK | B71: Mr. | C71: 39801649 | D71: pk.kasinathan@alba.com.bh | E71: Building 15, Road 94, Block 951, King Hamad Highway, Askar, Manama, P.O. Box 57, Kingdom of Bahrain. | F71: ALUMINIUM BAHRAIN B.S.C.(C) | G71: End Customer
A72: Mahmood Al Hamar | B72: Mr. | C72: 1783 0000 | D72: mahmood.abdulla@alba.com.bh | E72: Building 15, Road 94, Block 951, King Hamad Highway, Askar, Manama, P.O. Box 57, Kingdom of Bahrain. | F72: ALUMINIUM BAHRAIN B.S.C.(C) | G72: End Customer
A73: Mohammed A.Shaheed | B73: Mr. | C73: 1783 0000 | D73: mohammed.shaheed@alba.com.bh | E73: Building 15, Road 94, Block 951, King Hamad Highway, Askar, Manama, P.O. Box 57, Kingdom of Bahrain. | F73: ALUMINIUM BAHRAIN B.S.C.(C) | G73: End Customer
A74: P.K. Bhilare | B74: Mr. | C74: 1783 0000 | D74: pk.bhilare@alba.com.bh | E74: Building 15, Road 94, Block 951, King Hamad Highway, Askar, Manama, P.O. Box 57, Kingdom of Bahrain. | F74: ALUMINIUM BAHRAIN B.S.C.(C) | G74: End Customer
A75: Raffaele Zoli | B75: Mr. | C75: 38488100 | D75: raffaele.zoli@alba.com.bh | E75: Building 15, Road 94, Block 951, King Hamad Highway, Askar, Manama, P.O. Box 57, Kingdom of Bahrain. | F75: ALUMINIUM BAHRAIN B.S.C.(C) | G75: End Customer
A76: Samith rasane | B76: Mr. | C76: 17837974 | D76: samit.rasane@alba.com.bh | E76: Building 15, Road 94, Block 951, King Hamad Highway, Askar, Manama, P.O. Box 57, Kingdom of Bahrain. | F76: ALUMINIUM BAHRAIN B.S.C.(C) | G76: End Customer
A77: Sunil Kumar Gupta | B77: Mr. | C77: 1783 0000 | D77: sunil.gupta@alba.com.bh | E77: Building 15, Road 94, Block 951, King Hamad Highway, Askar, Manama, P.O. Box 57, Kingdom of Bahrain. | F77: ALUMINIUM BAHRAIN B.S.C.(C) | G77: End Customer
A78: Syed Ebrahim Alawi | B78: Mr. | C78: 1783 0000 | D78: sayed.ebrahim@alba.com.bh | E78: Building 15, Road 94, Block 951, King Hamad Highway, Askar, Manama, P.O. Box 57, Kingdom of Bahrain. | F78: ALUMINIUM BAHRAIN B.S.C.(C) | G78: End Customer
A79: Tawfiq Abdul Adwan | B79: Mr. | C79: 1783 0000 | D79: tawfiq.adwan@alba.com.bh | E79: Building 15, Road 94, Block 951, King Hamad Highway, Askar, Manama, P.O. Box 57, Kingdom of Bahrain. | F79: ALUMINIUM BAHRAIN B.S.C.(C) | G79: End Customer
... A89: Dikul Patel | B89: Mr. | C89: 37157470 | D89: dikulpatel@aquachemme.com | E89: Bahrain, Kingdom of Bahrain | F89: AQUACHEM | G89: National Reseller
A90: Brinto Varghese | B90: Mr. | D90: brinto.v@arabintl.com | E90: Manama, Kingdom of Bahrain | F90: Arab International | G90: Engineering Company, EPC/Licensor
A91: Rajesh Sharma | B91: Mr. | C91: +973 66734306 | D91: rajesh.sharma@arabintl.com | E91: Manama, Kingdom of Bahrain | F91: Arab International | G91: Engineering Company, EPC/Licensor
A92: vivek sharma | B92: Mr. | D92: vivek.sharma@arabintl.com | E92: Manama, Kingdom of Bahrain | F92: Arab International | G92: Engineering Company, EPC/Licensor
A93: Muhammad Munawwar Hassan | B93: Mr. | C93: (0)39514006 | D93: munawwar.hassan@star.adityabirla.com | E93: Bahrain, Kingdom of Bahrain | F93: Arab. Gulf Cement Co.. | G93: End Customer
A94: Ali Al-Afoo | B94: Mr. | C94: 17 510 914 | D94: a.alafow@ascsugar.com | E94: hidd, Kingdom of Bahrain | F94: Arab. Sugar Co. B.S.C | G94: End Customer
A95: Lateefuddin hasan quraishi | B95: Mr. | C95: (0)34045988 | D95: l.quraishi@ascsugar.com | E95: hidd, Kingdom of Bahrain | F95: Arab. Sugar Co. B.S.C | G95: End Customer
A96: S. Mohammed Alawi | B96: Mr. | C96: (0)38444398 | D96: s.maki@ascsugar.com | E96: hidd, Kingdom of Bahrain | F96: Arab. Sugar Co. B.S.C | G96: End Customer
A97: Muhammed Munawwar | B97: Mr. | C97: 17671011 | D97: munawwar.hassan@star.adityabirla.com | E97: Hidd, Kingdom of Bahrain | F97: Arabian Gulf Cement Co. Wll | G97: End Customer
A98: Sahil Choudhary | B98: Mr. | C98: 33976705 | D98: sahil.choudhary@star.adityabirla.com | E98: Hidd, Kingdom of Bahrain | F98: Arabian Gulf Cement Co. Wll | G98: End Customer
A99: Fujail Khan | B99: Mr. | C99: +973 6673 4356 | D99: info@arabintl.com | E99: Mahazzah, Sitra, Kingdom of Bahrain | F99: Arabian International Contracting | G99: Plant Builder
A100: Laxmi Narayan | B100: Mr. | C100: 39991248 | D100: laxmi.mahapatra@arabintl.com | E100: Mahazzah, Sitra, Kingdom of Bahrain | F100: Arabian International Contracting | G100: Plant Builder
A101: Mohammed Muddasir | B101: Mr. | C101: 17456532 | D101: muddasir.a@arabintl.com | E101: Mahazzah, Sitra, Kingdom of Bahrain | F101: Arabian International Contracting | G101: Plant Builder
A102: Salil Borkar | B102: Mr. | C102: 32239244 | D102: salil.borkar@arabintl.com | E102: Mahazzah, Sitra, Kingdom of Bahrain | F102: Arabian International Contracting | G102: Plant Builder
A103: Arif | B103: Mr. | C103: 1311 3540 | D103: ir@arabtecholding.com | E103: muharraq, Kingdom of Bahrain | F103: Arabtech -TAV | G103: Engineering Company, EPC/Licensor
A104: Inzamam Mushtaq | B104: Mr. | C104: 35343404/38850540 | D104: inmushtaq@arcenergy-bh.com | E104: Riffa, Kingdom of Bahrain | F104: ARC Energy | G104: National Reseller
... A113: Jalal Quawi | B113: Mr. | C113: 37779872 | D113: jalal@awaldairy.com | E113: al hajar, Kingdom of Bahrain | F113: Awal Dairy - Tetrapack | G113: End Customer
A114: Syed Omar | B114: Mr. | D114: business@awaldairy.com | E114: bahrain, Kingdom of Bahrain | F114: Awal Dairy Co. WLL | G114: End Customer
A115: Ram Kumar | B115: Mr. | C115: (0) 33218653 / 33393220 | D115: ram.p@aztec-gulf.com | E115: Riffa, Kingdom of Bahrain | F115: Aztec Services S.P.C | G115: Service Provider, Service Company
A116: Hussain Almeel | B116: Mr. | C116: +973 38838915 | D116: hussain.almeel@teekay.com | E116: Manama, Kingdom of Bahrain | F116: Bahrain LNG W.L.L | G116: End Customer
A117: Tim Clarke | B117: Mr. | C117: 37375555 | D117: timclarke@bahrainlng.com | E117: Manama, Kingdom of Bahrain | F117: Bahrain LNG W.L.L | G117: End Customer
A118: T. Babu Suresh | B118: Mr. | C118: (0)33543330 | D118: bsuresh@bmigp.com | E118: Bahrain, Kingdom of Bahrain | F118: Bahrain Medical | G118: End Customer
A119: Abdul samad | B119: Mr. | C119: 17750021 | D119: abdulsamad.hajres@banagas.com.bh | E119: Riffa, Kingdom of Bahrain | F119: Bahrain National Gas Company | G119: End Customer
A120: Anindya Nandy | B120: Mr. | C120: 17756991 | D120: anindya.nandy@banagas.com.bh | E120: Riffa, Kingdom of Bahrain | F120: Bahrain National Gas Company | G120: End Customer
A121: Sanjib changkakati | B121: Mr. | C121: 17752318 | D121: sanjib.changkakati@banagas.com.bh | E121: Riffa, Kingdom of Bahrain | F121: Bahrain National Gas Company | G121: End Customer
A122: Yousif ayoob | B122: Mr. | C122: 17752318 | D122: yousif.ayoob@banagas.com.bh | E122: Riffa, Kingdom of Bahrain | F122: Bahrain National Gas Company | G122: End Customer
A123: Muhammad Zishan | B123: Mr. | C123: 1610 0600 | D123: admin@gulf-biotech.com | E123: BIIP, Hidd, Kingdom of Bahrain | F123: Bahrain Pharma | G123: End Customer
A124: Leandra Ranges Escosio | B124: Mr. | C124: 17352350 | D124: leandra@foulath.com.bh | E124: Hidd, Kingdom of Bahrain | F124: Bahrain Steel BSCC (E.C.) - Sulb | G124: End Customer
A125: Maria Theresa Cruz | B125: Mr. | C125: 17352351 | D125: maria.theresa@foulath.com.bh | E125: Hidd, Kingdom of Bahrain | F125: Bahrain Steel BSCC (E.C.) - Sulb | G125: End Customer
A126: Micheal Jerold | B126: Mr. | C126: 17464222 | D126: mjerold@bahrainsteel.com.bh | E126: Hidd, Kingdom of Bahrain | F126: Bahrain Steel BSCC (E.C.) - Sulb | G126: End Customer
... A136: Ashvinkumar Behal | B136: Mr. | C136: 38885081 | D136: ashvin_behal@tatweerpetroleum.com | E136: P.O. Box 25555, Awali, Kingdom of Bahrain. | F136: BAPCO UPSTREAM W.L.L | G136: End Customer
A137: Hisham Alseba | B137: Mr. | D137: hisham_alseba@tatweerpetroleum.com | E137: P.O. Box 25555, Awali, Kingdom of Bahrain. | F137: BAPCO UPSTREAM W.L.L | G137: End Customer
A138: Isa abdulkarim | B138: Mr. | C138: 17148625 | D138: isa_abdulkarim@tatweerpetroleum.com | E138: P.O. Box 25555, Awali, Kingdom of Bahrain. | F138: BAPCO UPSTREAM W.L.L | G138: End Customer
A139: Jose Peter | B139: Mr. | C139: 38880456 | D139: jose_peter@tatweerpetroleum.com | E139: P.O. Box 25555, Awali, Kingdom of Bahrain. | F139: BAPCO UPSTREAM W.L.L | G139: End Customer
...
